LICENSE
MANIFEST.in
README.md
requirements.txt
setup.py
two/__init__.py
two/util.py
two.egg-info/PKG-INFO
two.egg-info/SOURCES.txt
two.egg-info/dependency_links.txt
two.egg-info/requires.txt
two.egg-info/top_level.txt
two.egg-info/zip-safe
two/src/data.txt