Metadata-Version: 2.1
Name: two
Version: 0.1.3
Summary: 😏随机一句「中二」的台词！
Home-page: https://github.com/Ailln/two
Author: Ailln
Author-email: kinggreenhall@gmail.com
License: MIT License
Platform: UNKNOWN
Classifier: Programming Language :: Python :: 3
Classifier: License :: OSI Approved :: MIT License
Classifier: Operating System :: OS Independent
